Metadata-Version: 1.0
Name: ds-distributions
Version: 0.1
Summary: Gaussian and Binomial distributions
Home-page: UNKNOWN
Author: Dewen Yushu
Author-email: dewenyushu@gmail.com
License: UNKNOWN
Platform: UNKNOWN
